llama_index/callbacks/argilla/__init__.py
llama_index/callbacks/argilla/base.py
llama_index_callbacks_argilla-0.4.1.dist-info/METADATA
llama_index_callbacks_argilla-0.4.1.dist-info/WHEEL
llama_index_callbacks_argilla-0.4.1.dist-info/licenses/LICENSE
llama_index_callbacks_argilla-0.4.1.dist-info/RECORD
