Metadata-Version: 2.4
Name: llama-index-callbacks-argilla
Version: 0.4.1
Summary: llama-index callbacks argilla integration
Author-email: Your Name <you@example.com>
License-Expression: MIT
License-File: LICENSE
Requires-Python: <3.12,>=3.9
Requires-Dist: argilla-llama-index>=1.0.0
Requires-Dist: argilla>=1.22.0
